{
	"backtraceGraph" : 
	{
		"commands" : 
		[
			"install"
		],
		"files" : 
		[
			"thirdparty/raygui/projects/CMake/CMakeLists.txt"
		],
		"nodes" : 
		[
			{
				"file" : 0
			},
			{
				"command" : 0,
				"file" : 0,
				"line" : 23,
				"parent" : 0
			}
		]
	},
	"installers" : 
	[
		{
			"backtrace" : 1,
			"component" : "Unspecified",
			"destination" : "include",
			"paths" : 
			[
				"thirdparty/raygui/projects/CMake/../../src/raygui.h"
			],
			"type" : "file"
		}
	],
	"paths" : 
	{
		"build" : "thirdparty/raygui/projects/CMake",
		"source" : "thirdparty/raygui/projects/CMake"
	}
}
